{
  "comment": "Sample data for google respnse when scope is profile, email, openid",

  "iss": "https://accounts.google.com",
  "azp": "201703575691-r9cbjb8a0nk5n3miidcfagk3t3non9nv.apps.googleusercontent.com",
  "aud": "201703575691-r9cbjb8a0nk5n3miidcfagk3t3non9nv.apps.googleusercontent.com",
  "sub": "110017476162236498769",
  "email": "blazingkrane@gmail.com",
  "email_verified": true,
  "at_hash": "azytDyZkRuEgo51zQtOmZg",
  "name": "Hussein Ibrahim",
  "picture": "https://lh3.googleusercontent.com/a/AAcHTtei3E7d4sAM8eVZiPZlL0IxA-YnVnkZp_m4CumF5A=s96-c",
  "given_name": "Hussein",
  "family_name": "Ibrahim",
  "locale": "en-GB",
  "iat": 1687384691,
  "exp": 1687388291
}
